Metadata-Version: 1.1
Name: fec
Version: 0.0
Summary: Simple FEC API wrapper
Home-page: http://jakekara.com
Author: Jake Kara
Author-email: jake@jakekara.com
License: UNKNOWN
Platform: UNKNOWN
Requires: requests
